{"povFiles":[{"urls":[{"url":"https://bit.ly/POVs_RaJo"}],"version":"1.0","id":"YvwC4DWd","updatedAt":1563141600000,"authors":["RajoJoey"],"game":{"id":"-bG4P570","name":"Rolling Stones"}}],"manufacturer":"Bally","topperFiles":[{"urls":[{"url":"https://vpuniverse.com/files/file/4749-topper-videos/"}],"version":"1.1.3","id":"CAe_4Dli","updatedAt":1498514400000,"authors":["Bambi Plattfuss"],"game":{"id":"-bG4P570","name":"Rolling Stones"}}],"mediaPackFiles":[{"urls":[{"url":"https://www.vpforums.org/index.php?app=downloads&showfile=4666"}],"version":"1.0.0","id":"Bd7ltdwy","updatedAt":1292108400000,"authors":["Bitupset"],"game":{"id":"-bG4P570","name":"Rolling Stones"}}],"MPU":"Bally MPU AS-2518-35","lastCreatedAt":1753401600000,"broken":false,"imgUrl":"https://virtualpinballspreadsheet.github.io/vps-db/img/-bG4P570_b2s_1698929000449.webp","designers":["Jim Patla"],"theme":["Celebrities","Licensed Theme","Music","Rock n roll"],"players":4,"wheelArtFiles":[{"urls":[{"url":"https://mega.nz/#F!p3hREDgB!pEWMJvVQ7t3Sv_TmrxdU-w!52AzHIDR"}],"version":"1.0","id":"tbpv0R1x","updatedAt":1517439600000,"authors":["Calium"],"game":{"id":"-bG4P570","name":"Rolling Stones"}}],"ipdbUrl":"http://www.ipdb.org/machine.cgi?id=2010","year":1980,"type":"SS","name":"Rolling Stones","id":"-bG4P570","tableFiles":[{"id":"4C2p4x_l","features":["SSF","LUT"],"createdAt":1753401600000,"game":{"id":"-bG4P570","name":"Rolling Stones"},"imgUrl":"https://virtualpinballspreadsheet.github.io/vps-db/img/4C2p4x_l_1753718101094.webp","tableFormat":"VPX","updatedAt":1753718102314,"urls":[{"url":"https://www.vpforums.org/index.php?app=downloads&showfile=12914"}],"authors":["JPSalas","HauntFreaks","RipleYYY","Xenonph","Mustang1961"],"version":"5.5.1"},{"authors":["Larouillas","HauntFreaks","JPSalas"],"imgUrl":"https://virtualpinballspreadsheet.github.io/vps-db/img/tZr2jk-Sb0_1727864198637.webp","createdAt":1727913600000,"version":"1.0.0","comment":"Table + PuP-Pack. Black and White MOD","id":"tZr2jk-Sb0","features":["MOD","incl. PuP","incl. B2S"],"updatedAt":1728039290244,"edition":"Black and White Edition","tableFormat":"VPX","game":{"id":"-bG4P570","name":"Rolling Stones"},"urls":[{"url":"https://vpuniverse.com/files/file/21823-rolling-stones-pup-bw-bally-1979/"}]},{"updatedAt":1640278942755,"id":"RaW22XHj","authors":["HiRez00","JPSalas","Goldchicco"],"tableFormat":"VPX","version":"1.1","imgUrl":"https://virtualpinballspreadsheet.github.io/vps-db/img/f2f58d190a45346ba0053237cea2943e_table_1640278965058.webp","comment":"See Description on download page for Music files","game":{"id":"-bG4P570","name":"Rolling Stones"},"urls":[{"url":"https://vpuniverse.com/files/file/8493-rolling-stones-the-bally-1980-11-vpx-extras/"}],"createdAt":1640127600000,"features":["Music","incl. Art"]},{"id":"8ODDlgBrPg","createdAt":1624838400000,"updatedAt":1748190737681,"urls":[{"url":"https://www.vpforums.org/index.php?app=downloads&showfile=15926","broken":false}],"authors":["Bigus1","JPSalas"],"features":["FSS","MOD"],"tableFormat":"VPX","imgUrl":"https://virtualpinballspreadsheet.github.io/vps-db/img/8ODDlgBrPg_1747194779665.webp","comment":"Bigus MOD","version":"1.0","game":{"id":"-bG4P570","name":"Rolling Stones"}},{"id":"CqL5ibkl","tableFormat":"VPX","authors":["iDigStuff","JPSalas"],"version":"1.2","createdAt":1616886000000,"urls":[{"url":"https://vpuniverse.com/files/file/5944-rolling-stones-bally-1979-%E2%80%93-idig-remix/"}],"comment":"iDig rEMix Vol. 2 - Music MOD","updatedAt":1616886000000,"imgUrl":"https://virtualpinballspreadsheet.github.io/vps-db/img/f2f58d190a45346ba0053237cea2943e_table_1638093698422.webp","game":{"id":"-bG4P570","name":"Rolling Stones"},"features":["Music","MOD"]}],"b2sFiles":[{"game":{"id":"-bG4P570","name":"Rolling Stones"},"createdAt":1739059200000,"authors":["HauntFreaks"],"updatedAt":1739101739596,"version":"2.0","urls":[{"url":"https://vpuniverse.com/files/file/16581-rolling-stones-bally-1980-b2s/"}],"id":"0GMLaAWtSb","imgUrl":"https://virtualpinballspreadsheet.github.io/vps-db/img/0GMLaAWtSb_1739101738302.webp","features":["3Screens"]},{"version":"1.1","authors":["HiRez00"],"imgUrl":"https://virtualpinballspreadsheet.github.io/vps-db/img/f2f58d190a45346ba0053237cea2943e_b2s_1641064402546.webp","createdAt":1640278988322,"updatedAt":1640278994131,"id":"ttJyiAFo","features":["2Screens"],"urls":[{"url":"https://vpuniverse.com/files/file/8490-rolling-stones-bally-1980-11-b2s/"}],"game":{"id":"-bG4P570","name":"Rolling Stones"}},{"updatedAt":1362092400000,"authors":["Herweh"],"id":"kj0vh8uP","game":{"id":"-bG4P570","name":"Rolling Stones"},"features":["2Screens"],"version":"1.1","imgUrl":"https://virtualpinballspreadsheet.github.io/vps-db/img/f2f58d190a45346ba0053237cea2943e_b2s_1638093707591.webp","urls":[{"url":"https://www.vpforums.org/index.php?app=downloads&showfile=7541"}]}],"updatedAt":1753718102314,"romFiles":[{"urls":[{"url":"https://www.vpforums.org/index.php?app=downloads&showfile=681"}],"comment":"7-digit","updatedAt":1740395416823,"version":"rollstob","id":"GD99CO7e","authors":["Destruk"],"createdAt":1359331200000,"game":{"id":"-bG4P570","name":"Rolling Stones"}}]}