{"id":"02zHuea_Pf","updatedAt":1739022012138,"manufacturer":"Williams","name":"Zodiac","year":1971,"theme":["Astrology"],"designers":["Steve Kordek"],"type":"EM","players":2,"ipdbUrl":"https://www.ipdb.org/machine.cgi?id=2841","tableFiles":[{"id":"kc1FB8NS08","createdAt":1738368000000,"updatedAt":1739022012138,"urls":[{"url":"https://vpuniverse.com/files/file/23733-zodiac-williams-1971/","broken":false}],"authors":["Itchigo","Drinkcristal","Polsonator2"],"features":["no ROM","incl. B2S"],"tableFormat":"VPX","version":"1.0.0","imgUrl":"https://virtualpinballspreadsheet.github.io/vps-db/img/kc1FB8NS08_1739022010948.webp","game":{"id":"02zHuea_Pf","name":"Zodiac"}}],"b2sFiles":[{"id":"Yjg8ZKTJ1W","createdAt":1738368000000,"updatedAt":1739022029753,"urls":[{"url":"https://vpuniverse.com/files/file/23733-zodiac-williams-1971/","broken":false}],"authors":["Itchigo"],"features":[],"version":"1.0.0","imgUrl":"https://virtualpinballspreadsheet.github.io/vps-db/img/Yjg8ZKTJ1W_1739022028396.webp","game":{"id":"02zHuea_Pf","name":"Zodiac"}}],"lastCreatedAt":1738368000000}