{"year":1931,"updatedAt":1617141600000,"designers":[],"tableFiles":[{"version":"1.0","id":"tv6Y6G8fNi","game":{"id":"7g5lRPR4ZD","name":"Polo Skill"},"updatedAt":1647272294750,"tableFormat":"VPX","createdAt":1617141600000,"urls":[{"url":"https:\/\/pinballnirvana.com\/forums\/resources\/polo-skill-a-pirmischer-1931-vpx.5891\/"}],"features":["no ROM"],"authors":["Druadic"],"imgUrl":"https:\/\/virtualpinballspreadsheet.github.io\/vps-db\/img\/undefined_table_1647272360868.webp"}],"lastCreatedAt":1617141600000,"id":"7g5lRPR4ZD","theme":["Polo","Flipperless"],"name":"Polo Skill","broken":false,"type":"PM","manufacturer":"A. Pirmischer","players":1}