{"id":"7jN8q3noP6","updatedAt":1734952363204,"manufacturer":"Original","name":"Nightmare Before Christmas","year":2024,"theme":["Animation","Fantasy"],"designers":[],"type":"SS","players":4,"tableFiles":[{"id":"LI9FmU9PDM","createdAt":1734134400000,"updatedAt":1734952363204,"urls":[{"url":"https://vpuniverse.com/files/file/22643-nightmare-before-christmas2024/","broken":false}],"authors":["Tartzani","Oqqsan","JoePicasso","iDigStuff","Apophis","DaRdog81","DarinVPCLE","HauntFreaks","Zandy's Arcade","wolfman","JPSalas"],"features":["Hybrid","VR","FSS","SSF","nFozzy","Fleep"],"tableFormat":"VPX","imgUrl":"https://virtualpinballspreadsheet.github.io/vps-db/img/LI9FmU9PDM_1734110160948.webp","version":"1.0.2","game":{"id":"7jN8q3noP6","name":"Nightmare Before Christmas"}}],"b2sFiles":[{"id":"Tyz4DkD1by","createdAt":1734109035098,"updatedAt":1734109131588,"urls":[{"url":"https://vpuniverse.com/files/file/22642-nightmare-before-christmas-original-2024-b2s-full-dmd/","broken":false}],"authors":["HauntFreaks","JoePicasso"],"features":["FullDMD","2Screens"],"imgUrl":"https://virtualpinballspreadsheet.github.io/vps-db/img/Tyz4DkD1by_1734109045101.webp","version":"1.0","game":{"id":"7jN8q3noP6","name":"Nightmare Before Christmas"}}],"lastCreatedAt":1734134400000,"tutorialFiles":[{"id":"svo2YxVuU6","createdAt":1734348511877,"updatedAt":1734385340592,"authors":["Kongedam","Odradek"],"youtubeId":"btGfF1V68p4","game":{"id":"7jN8q3noP6","name":"Nightmare Before Christmas"},"title":"Nightmare Before Christmas"}],"ruleFiles":[{"id":"7LiXcWNco5","createdAt":1734348519583,"updatedAt":1734717143946,"urls":[{"url":"https://vpuniverse.com/files/file/22629-nightmare-before-christmas-original-2024-vpx-video-instruction/","broken":false}],"authors":["Kongedam","Odradek"],"comment":"Video","game":{"id":"7jN8q3noP6","name":"Nightmare Before Christmas"},"version":"1.0.0"},{"id":"nIoR3zju_a","createdAt":1734048000000,"updatedAt":1734716879776,"urls":[{"url":"https://vpuniverse.com/files/file/22647-nightmare-before-christmas-help-instruction-card-set-portrait-landscape-ltek/","broken":false}],"authors":["LTek"],"version":"1.0.0","game":{"id":"7jN8q3noP6","name":"Nightmare Before Christmas"}}],"pupPackFiles":[{"id":"zoLTjxJqwT","createdAt":1734392059675,"updatedAt":1734392103199,"urls":[{"url":"https://vpuniverse.com/files/file/22679-nightmare-before-christmas-pup-pack/","broken":false}],"authors":["GtecArcade"],"version":"1.0.1","game":{"id":"7jN8q3noP6","name":"Nightmare Before Christmas"}}]}