{"id":"bOHzDcbn9W","updatedAt":1715510371825,"manufacturer":"Original","name":"Barnstorming","year":2024,"theme":["Aircraft"],"designers":[],"type":"EM","players":4,"tableFiles":[{"id":"KL_qEMz_Ph","createdAt":1715472000000,"updatedAt":1715510371825,"urls":[{"url":"https://www.vpforums.org/index.php?app=downloads&showfile=18414","broken":false}],"authors":["Xfl","JPSalas"],"features":["no ROM","incl. B2S"],"tableFormat":"VPX","version":"0.2","imgUrl":"https://virtualpinballspreadsheet.github.io/vps-db/img/KL_qEMz_Ph_1714093447134.webp","comment":"Based on JPSalas's Stardust (Williams 1971)","game":{"id":"bOHzDcbn9W","name":"Barnstorming"}}],"b2sFiles":[{"id":"lBWfzDBdeG","createdAt":1714003200000,"updatedAt":1714093513527,"urls":[{"url":"https://www.vpforums.org/index.php?app=downloads&showfile=18414","broken":false}],"authors":["Xfl"],"features":[],"imgUrl":"https://virtualpinballspreadsheet.github.io/vps-db/img/lBWfzDBdeG_1714093482076.webp","version":"0.0","comment":"Included with table download","game":{"id":"bOHzDcbn9W","name":"Barnstorming"}}],"lastCreatedAt":1715472000000}