{"povFiles":[{"updatedAt":1563141600000,"urls":[{"url":"https:\/\/bit.ly\/POVs_RaJo"}],"authors":["RajoJoey"],"game":{"name":"Missing in Action","id":"C0fxFpTh"},"version":"1.0","id":"xHxKnFkW"}],"manufacturer":"Original","broken":false,"lastCreatedAt":1541458800000,"designers":[],"theme":["Movie"],"wheelArtFiles":[{"updatedAt":1540854000000,"urls":[{"url":"https:\/\/mega.nz\/#F!p3hREDgB!pEWMJvVQ7t3Sv_TmrxdU-w!52AzHIDR"}],"authors":["Calium"],"game":{"name":"Missing in Action","id":"C0fxFpTh"},"version":"1.0","id":"r2mdEHNV"}],"year":2018,"type":"SS","name":"Missing in Action","id":"C0fxFpTh","b2sFiles":[{"updatedAt":1647343191816,"game":{"id":"C0fxFpTh","name":"Missing in Action"},"id":"G3E7mfWHco","authors":["Larouillas"],"createdAt":1647343188575,"urls":[{"url":"https:\/\/vpuniverse.com\/files\/file\/8733-missing-in-action\/"}],"imgUrl":"https:\/\/virtualpinballspreadsheet.github.io\/vps-db\/img\/C0fxFpTh_b2s_1647874877522.webp","version":"1.0.0"}],"tableFiles":[{"updatedAt":1541458800000,"game":{"id":"C0fxFpTh","name":"Missing in Action"},"id":"FBS7GRT_","urls":[{"url":"https:\/\/www.vpforums.org\/index.php?app=downloads&showfile=13805"}],"tableFormat":"VPX","comment":"Reskin of El Bueno el Feo y el Mao (Original 2015)","authors":["Ivantba","Xenonph","JPSalas"],"version":"1.1","createdAt":1541458800000,"imgUrl":"https:\/\/virtualpinballspreadsheet.github.io\/vps-db\/img\/51e0e1b55acfa7d800c148f189f5e750_table_1638093698337.webp"}],"updatedAt":1541458800000,"romFiles":[{"updatedAt":1711218249167,"authors":["Destruk"],"version":"eldorado","urls":[{"url":"https:\/\/www.vpforums.org\/index.php?app=downloads&showfile=1041","broken":true}],"createdAt":1359158400000,"game":{"id":"C0fxFpTh","name":"Missing in Action"},"id":"CfSOb-dk","comment":"Distribution denied"}]}