{"wheelArtFiles":[{"game":{"name":"Terminator Salvation","id":"gi4A1Wz1"},"version":"1.0","id":"4geKE2Tn","authors":["Calium"],"urls":[{"url":"https:\/\/mega.nz\/?fbclid=IwAR3wuVW9PmQY8pCaogSV93FUFAJOkRJkmAc_U94zj5yJ6T-IDU6ONeAYNlU#F!E6AC2bYL!Jv2_vxZ--OCWhhU97rmDVw"}],"updatedAt":1540854000000}],"broken":false,"designers":[],"povFiles":[{"game":{"id":"gi4A1Wz1","name":"Terminator Salvation"},"version":"1.0","id":"1_z8--4H","authors":["RajoJoey"],"urls":[{"url":"https:\/\/bit.ly\/POVs_RaJo"}],"updatedAt":1563141600000}],"year":2018,"name":"Terminator Salvation","theme":["Movie","Science Fiction","Apocalyptic"],"updatedAt":1552172400000,"id":"gi4A1Wz1","tableFiles":[{"imgUrl":"https:\/\/virtualpinballspreadsheet.github.io\/vps-db\/img\/be8f5284b091b2270a173d05fb23590e_table_1638094245046.webp","id":"qt4NQBef","urls":[{"url":"https:\/\/www.vpforums.org\/index.php?app=downloads&showfile=13772"}],"updatedAt":1552172400000,"game":{"name":"Terminator Salvation","id":"gi4A1Wz1"},"version":"1.4d","authors":["Ivantba","STAT","JPSalas"],"tableFormat":"VPX","features":["MOD"],"comment":"Reskin of JPSalas' Serious Sam Pinball (Original 2017)","createdAt":1552172400000}],"lastCreatedAt":1552172400000,"b2sFiles":[{"version":"1.0.0","id":"3J-NAVNT","imgUrl":"https:\/\/virtualpinballspreadsheet.github.io\/vps-db\/img\/be8f5284b091b2270a173d05fb23590e_b2s_1638358872442.webp","urls":[{"url":"https:\/\/vpuniverse.com\/files\/file\/7928-terminator-salvation\/"}],"game":{"id":"gi4A1Wz1","name":"Terminator Salvation"},"createdAt":1638267549175,"authors":["Larouillas"],"updatedAt":1638267563593}],"type":"SS","manufacturer":"Original"}