{"theme":["Adventure","Fantasy"],"name":"El Dorado City of Gold","MPU":"Gottlieb System 80A","wheelArtFiles":[{"updatedAt":1638394374504,"game":{"name":"El Dorado City of Gold","id":"hCFbHPQd"},"authors":["Mkl66"],"urls":[{"url":"https:\/\/vpuniverse.com\/files\/file\/6601-el-dorado-city-of-gold-premier-1984\/"}],"createdAt":1638394365813,"id":"o9GkSCCk"}],"topperFiles":[{"updatedAt":1506981600000,"game":{"id":"hCFbHPQd","name":"El Dorado City of Gold"},"authors":["Bambi Plattfuss"],"urls":[{"url":"https:\/\/vpuniverse.com\/files\/file\/4749-topper-videos\/"}],"version":"1.3.7","id":"mxoNFrLo"},{"id":"r4bpYk64GP","game":{"id":"hCFbHPQd","name":"El Dorado City of Gold"},"authors":["Guet35"],"updatedAt":1734186616654,"version":"1.0","urls":[{"url":"https:\/\/vpuniverse.com\/files\/file\/22581-el-dorado-city-of-gold-gottlieb-1984-topper-video\/"}],"createdAt":1734186601829}],"id":"hCFbHPQd","broken":false,"ipdbUrl":"http:\/\/www.ipdb.org\/machine.cgi?id=767","tutorialFiles":[{"id":"qte1v6bqpa","title":" El Dorado City of Gold","game":{"name":"El Dorado City of Gold","id":"hCFbHPQd"},"updatedAt":1755904242095,"authors":["Pinball Primer"],"url":"https:\/\/pinballprimer.github.io\/eldoradocog_GrEZ5.html","createdAt":1755904242095}],"b2sFiles":[{"id":"gbheO0bS","game":{"id":"hCFbHPQd","name":"El Dorado City of Gold"},"updatedAt":1638394407799,"version":"1.1","urls":[{"url":"https:\/\/vpuniverse.com\/files\/file\/4637-el-dorado-city-of-gold-premier-1984\/"}],"createdAt":1638394395965,"authors":["Wildman"],"imgUrl":"https:\/\/virtualpinballspreadsheet.github.io\/vps-db\/img\/7301360eafc4035c9375aa309544eada_b2s_1638394496162.webp"}],"year":1984,"players":4,"tableFiles":[{"features":["SSF","MOD"],"updatedAt":1638394232867,"version":"1.3","imgUrl":"https:\/\/virtualpinballspreadsheet.github.io\/vps-db\/img\/7301360eafc4035c9375aa309544eada_table_1638394242547.webp","authors":["Jbg4208","TheGhost787","Thalamus","Outhere","BorgDog","Ninuzzu","32assassin","nFozzy"],"tableFormat":"VPX","game":{"name":"El Dorado City of Gold","id":"hCFbHPQd"},"createdAt":1624917600000,"id":"87kGZfZY","urls":[{"url":"https:\/\/vpuniverse.com\/files\/file\/4635-el-dorado-city-of-gold\/"}]},{"authors":["TheGhost787","32assassin"],"urls":[{"url":"https:\/\/www.vpforums.org\/index.php?app=downloads&showfile=12594"}],"createdAt":1484953200000,"imgUrl":"https:\/\/virtualpinballspreadsheet.github.io\/vps-db\/img\/7301360eafc4035c9375aa309544eada_table_1638093698177.webp","updatedAt":1484953200000,"game":{"name":"El Dorado City of Gold","id":"hCFbHPQd"},"id":"qy0LZKZa","version":"1.0","features":["MOD"],"tableFormat":"VPX"}],"manufacturer":"Gottlieb","updatedAt":1638394232867,"designers":["Ed Krynski"],"type":"SS","povFiles":[{"updatedAt":1563141600000,"game":{"name":"El Dorado City of Gold","id":"hCFbHPQd"},"authors":["RajoJoey"],"urls":[{"url":"https:\/\/bit.ly\/POVs_RaJo"}],"version":"1.0","id":"Xi38_7ZX"}],"lastCreatedAt":1624917600000}