{"povFiles":[{"game":{"id":"MBZPVX6p","name":"Defender"},"id":"L6Yb4XdX","updatedAt":1563141600000,"authors":["RajoJoey"],"version":"1.0","urls":[{"url":"https://bit.ly/POVs_RaJo"}]}],"manufacturer":"Williams","topperFiles":[{"updatedAt":1648477731074,"version":"1.0.0","createdAt":1648477721969,"id":"Tbdz1SmLlB","urls":[{"url":"https://vpuniverse.com/files/file/9458-defender-topper-et-fulldmd/"}],"game":{"id":"MBZPVX6p","name":"Defender"},"authors":["Guet35"]}],"mediaPackFiles":[{"game":{"id":"MBZPVX6p","name":"Defender"},"id":"97DR8HCG","updatedAt":1708681419485,"authors":["GTXJoe"],"version":"1.0.0","urls":[{"url":"https://www.vpforums.org/index.php?app=downloads&showfile=8829"}]}],"MPU":"Williams System 7","lastCreatedAt":1750723200000,"broken":false,"imgUrl":"https://virtualpinballspreadsheet.github.io/vps-db/img/5985171c62d29ef27102ffc2ce3f3376_b2s_1638093727198.webp","designers":["Barry Oursler"],"players":2,"theme":["Outer Space","Fantasy","Video Game"],"wheelArtFiles":[{"updatedAt":1647093062848,"createdAt":1647093049450,"authors":["HauntFreaks"],"game":{"id":"MBZPVX6p","name":"Defender"},"urls":[{"url":"https://vpuniverse.com/files/file/9461-defender-williams-1982-ani-wheel/"}],"id":"CB64vNs86B","version":"1.0.0"},{"game":{"id":"MBZPVX6p","name":"Defender"},"id":"w2MZUR5G","updatedAt":1517439600000,"authors":["Calium"],"version":"1.0","urls":[{"url":"https://mega.nz/#F!p3hREDgB!pEWMJvVQ7t3Sv_TmrxdU-w!52AzHIDR"}]}],"type":"SS","ipdbUrl":"http://www.ipdb.org/machine.cgi?id=651","year":1982,"name":"Defender","ruleFiles":[{"urls":[{"url":"https://vpuniverse.com/files/file/21192-defender-williams-1982-vpx-video-instruction/"}],"game":{"id":"MBZPVX6p","name":"Defender"},"createdAt":1733859805592,"version":"1.0","updatedAt":1733861058270,"authors":["Kongedam","Odradek"],"comment":"Video","id":"5p6G9CHucH"},{"game":{"id":"MBZPVX6p","name":"Defender"},"authors":["Nevvyboy"],"urls":[{"url":"https://vpuniverse.com/files/file/19237-defender-williams-1982-vpx-instructions/"}],"createdAt":1711324800000,"updatedAt":1713879782208,"id":"SStVQ47g0I","version":"1.0.0"}],"id":"MBZPVX6p","tutorialFiles":[{"game":{"id":"MBZPVX6p","name":"Defender"},"createdAt":1722522137102,"youtubeId":"ny85E33YSZQ","id":"R4UCgTzUhU","authors":["Kongedam","Odradek"],"updatedAt":1733859798458,"title":"Defender (Williams 1982) - VPX Video Instruction"}],"tableFiles":[{"imgUrl":"https://virtualpinballspreadsheet.github.io/vps-db/img/5985171c62d29ef27102ffc2ce3f3376_table_1638093698157.webp","comment":"Bigus MOD","updatedAt":1750808289822,"urls":[{"url":"https://www.vpforums.org/index.php?app=downloads&showfile=14314"}],"createdAt":1750723200000,"game":{"id":"MBZPVX6p","name":"Defender"},"authors":["Bigus1","Takut","GTXJoe"],"tableFormat":"VPX","features":["MOD","FlexDMD"],"version":"3.1","id":"VCwWnvjE"},{"urls":[{"url":"https://vpuniverse.com/files/file/9456-defender-williams-1982-vpw/"}],"createdAt":1711152000000,"imgUrl":"https://virtualpinballspreadsheet.github.io/vps-db/img/MBZPVX6p_table_1647092882908.webp","tableFormat":"VPX","comment":"","updatedAt":1711114437799,"id":"XJIqrWKHAC","version":"1.3","game":{"id":"MBZPVX6p","name":"Defender"},"authors":["VPW"],"features":["VR","Hybrid","SSF","FSS","nFozzy","Fleep","FlexDMD"]},{"updatedAt":1716780258870,"version":"1.0.0","edition":"VR","imgUrl":"https://virtualpinballspreadsheet.github.io/vps-db/img/MBZPVX6p_table_1673760811877.webp","game":{"id":"MBZPVX6p","name":"Defender"},"createdAt":1649887200000,"features":["VR"],"id":"OIUHRT-c","comment":"","authors":["Takut","GTXJoe"],"urls":[{"url":"https://vpuniverse.com/files/file/9869-vr-room-defender-williams-1982/"}],"tableFormat":"VPX"},{"id":"T9udbILn","version":"1.0","urls":[{"url":"https://www.vpforums.org/index.php?app=downloads&showfile=12676"}],"updatedAt":1486854000000,"tableFormat":"VPX","imgUrl":"https://virtualpinballspreadsheet.github.io/vps-db/img/MBZPVX6p_table_1647092790947.webp","createdAt":1486854000000,"game":{"id":"MBZPVX6p","name":"Defender"},"authors":["32assassin","GTXJoe"],"features":[]}],"b2sFiles":[{"game":{"id":"MBZPVX6p","name":"Defender"},"updatedAt":1710068216847,"authors":["HauntFreaks"],"features":["2Screens","3Screens"],"urls":[{"url":"https://vpuniverse.com/files/file/9460-defender-williams-1982-2-3srn-b2s/"}],"version":"2.0","createdAt":1705795200000,"imgUrl":"https://virtualpinballspreadsheet.github.io/vps-db/img/uliKM1DyCO_1710068168181.webp","id":"M43fmxnsBe"},{"game":{"id":"MBZPVX6p","name":"Defender"},"updatedAt":1710069528447,"id":"t3bs679t-K","version":"1.0.0","createdAt":1705795200000,"authors":["HauntFreaks"],"imgUrl":"https://virtualpinballspreadsheet.github.io/vps-db/img/t3bs679t-K_1710069509720.webp","urls":[{"url":"https://vpuniverse.com/files/file/18128-defender-williams-1982-b2s-with-full-dmd/"}],"features":["FullDMD"]},{"version":"1.0","authors":["WalterWhite"],"urls":[{"url":"https://vpuniverse.com/files/file/12069-defender-fulldmd-williams-1982/"}],"game":{"id":"MBZPVX6p","name":"Defender"},"features":["FullDMD"],"updatedAt":1667746328361,"id":"nh9KdY-cD_","createdAt":1667746310898,"comment":"","imgUrl":"https://virtualpinballspreadsheet.github.io/vps-db/img/MBZPVX6p_b2s_1667746318575.webp"},{"id":"EYeypIjp","version":"1.0","createdAt":1387584000000,"game":{"id":"MBZPVX6p","name":"Defender"},"urls":[{"url":"https://www.vpforums.org/index.php?app=downloads&showfile=8803"}],"authors":["Piggei (PJ)"],"updatedAt":1710068238723,"imgUrl":"https://virtualpinballspreadsheet.github.io/vps-db/img/5985171c62d29ef27102ffc2ce3f3376_b2s_1638093727198.webp"}],"updatedAt":1750808289822,"romFiles":[{"game":{"id":"MBZPVX6p","name":"Defender"},"id":"se0sPXV5","updatedAt":1359154800000,"authors":["Destruk"],"version":"dfndr_l4","urls":[{"url":"https://www.vpforums.org/index.php?app=downloads&showfile=805"}]}],"soundFiles":[{"game":{"id":"MBZPVX6p","name":"Defender"},"id":"WCStORxt5I","updatedAt":946681200000,"version":"","urls":[{"url":"https://www.dropbox.com/s/6ydx4edmvlghzca/Defender%20%28Williams%201982%29.mp3?dl=0"}]}]}