{"b2sFiles":[{"id":"91lVBYjTvb","urls":[{"url":"https:\/\/vpuniverse.com\/files\/file\/18877-king-pin-gottlieb-1973\/"}],"authors":["Wildman"],"createdAt":1709337600000,"version":"1.0.0","updatedAt":1709661784417,"game":{"id":"MCxB4Iuu","name":"King Pin"},"imgUrl":"https:\/\/virtualpinballspreadsheet.github.io\/vps-db\/img\/91lVBYjTvb_1709661782336.webp"}],"players":1,"tableFiles":[{"features":["VR","Hybrid","incl. B2S","no ROM","LUT"],"tableFormat":"VPX","authors":["RajoJoey","Loserman76","GNance","Popotte"],"game":{"id":"MCxB4Iuu","name":"King Pin"},"imgUrl":"https:\/\/virtualpinballspreadsheet.github.io\/vps-db\/img\/MCxB4Iuu_table_1672922698217.webp","version":"1.0.0","createdAt":1672786800000,"updatedAt":1672922655861,"urls":[{"url":"https:\/\/vpuniverse.com\/files\/file\/12647-king-pin-gottlieb-1973-vr-room\/"}],"id":"_Ofc0ddQ2Q","comment":""},{"features":["incl. B2S","no ROM"],"tableFormat":"VPX","authors":["Loserman76","GNance","Popotte","Pinuck","BorgDog","Arngrim","HauntFreaks","JPSalas"],"game":{"id":"MCxB4Iuu","name":"King Pin"},"imgUrl":"https:\/\/virtualpinballspreadsheet.github.io\/vps-db\/img\/ea90bd929be4675d79e02d117d37799a_table_1640003618777.webp","version":"1.0.0f","createdAt":1639004400000,"updatedAt":1640003444352,"urls":[{"url":"https:\/\/vpuniverse.com\/files\/file\/8291-king-pin-gottlieb-1973\/"},{"url":"https:\/\/www.vpforums.org\/index.php?app=downloads&showfile=13226"}],"id":"Otk9YKG2","comment":"Reupload"}],"name":"King Pin","manufacturer":"Gottlieb","updatedAt":1672922655861,"povFiles":[{"updatedAt":1563141600000,"game":{"id":"MCxB4Iuu","name":"King Pin"},"id":"r1Ys9f0E","urls":[{"url":"https:\/\/bit.ly\/POVs_RaJo"}],"authors":["RajoJoey"],"version":"1.0"}],"broken":false,"id":"MCxB4Iuu","wheelArtFiles":[{"updatedAt":1517439600000,"game":{"name":"King Pin","id":"MCxB4Iuu"},"id":"caLZdfmT","urls":[{"url":"https:\/\/mega.nz\/#F!p3hREDgB!pEWMJvVQ7t3Sv_TmrxdU-w!52AzHIDR"}],"authors":["Calium"],"version":"1.0"}],"year":1973,"designers":["Ed Krynski"],"type":"EM","ipdbUrl":"http:\/\/www.ipdb.org\/machine.cgi?id=1374","tutorialFiles":[{"id":"dl72_0haTH","authors":["Pinball Primer"],"updatedAt":1755904241870,"game":{"name":"King Pin","id":"MCxB4Iuu"},"createdAt":1755904241870,"title":" King Pin","url":"https:\/\/pinballprimer.github.io\/kingpin_GR6DZ.html"}],"theme":["Sports","Bowling"],"lastCreatedAt":1672786800000}