{"name":"Old Coney Island!","id":"oA-XPy3V","manufacturer":"Game Plan","year":1979,"MPU":"Game Plan MPU-2","theme":["Happiness","Circus","Carnival"],"players":4,"designers":["Ed Cebula"],"ipdbUrl":"http://www.ipdb.org/machine.cgi?id=553","type":"SS","updatedAt":1702040722266,"tableFiles":[{"id":"z4uQwFVcHu","createdAt":1701903600000,"updatedAt":1702040722266,"theme":["Happiness","Circus","Carnival"],"tableFormat":"VPX","comment":"VR Room","features":["VR","incl. B2S"],"urls":[{"url":"https://vpuniverse.com/files/file/17443-old-coney-island-game-plan-1979-jp-v402-ext2k-vrroom/"},{"url":"https://www.vpforums.org/index.php?app=downloads&showfile=18026"}],"authors":["Ext2k","JPSalas"],"version":"1.0.0","imgUrl":"https://virtualpinballspreadsheet.github.io/vps-db/img/oA-XPy3V_table_1702040746078.webp","game":{"id":"oA-XPy3V","name":"Old Coney Island!"}},{"urls":[{"url":"http://www.vpforums.org/index.php?app=downloads&showfile=12546","broken":false}],"theme":["Happiness","Circus","Carnival"],"version":"4.0.2","authors":["JPSalas"],"updatedAt":1666880543768,"createdAt":1666843200000,"tableFormat":"VPX","imgUrl":"https://virtualpinballspreadsheet.github.io/vps-db/img/493ed8e743f086641e0f3397e697b720_table_1638093698370.webp","id":"vSXyqxaC","features":["LUT"],"game":{"id":"oA-XPy3V","name":"Old Coney Island!"}}],"b2sFiles":[{"id":"PUPYMHw6pE","createdAt":1722211200000,"updatedAt":1731570914202,"urls":[{"url":"https://vpuniverse.com/files/file/21166-old-coney-island-game-plan-1979-b2s/","broken":false}],"authors":["HauntFreaks"],"features":["2Screens","3Screens"],"imgUrl":"https://virtualpinballspreadsheet.github.io/vps-db/img/PUPYMHw6pE_1731570882925.webp","version":"1.0.0","game":{"id":"oA-XPy3V","name":"Old Coney Island!"}},{"urls":[{"url":"http://www.vpforums.org/index.php?app=downloads&showfile=12547","broken":false}],"version":"1.2","authors":["STAT","JPSalas"],"updatedAt":1482274800000,"imgUrl":"https://virtualpinballspreadsheet.github.io/vps-db/img/493ed8e743f086641e0f3397e697b720_b2s_1638093742641.webp","id":"ezz3JeOf","game":{"id":"oA-XPy3V","name":"Old Coney Island!"},"features":[]}],"romFiles":[{"version":"coneyis","urls":[{"url":"https://www.vpforums.org/index.php?app=downloads&showfile=536","broken":false}],"authors":["Destruk"],"updatedAt":1359154800000,"id":"VCxbXX4J","game":{"id":"oA-XPy3V","name":"Old Coney Island!"}}],"povFiles":[{"version":"1.0","urls":[{"url":"http://bit.ly/POVs_RaJo","broken":false}],"authors":["RajoJoey"],"updatedAt":1563141600000,"id":"MPTQy5m8","game":{"id":"oA-XPy3V","name":"Old Coney Island!"}}],"wheelArtFiles":[{"urls":[{"url":"https://mega.nz/#F!p3hREDgB!pEWMJvVQ7t3Sv_TmrxdU-w!52AzHIDR","broken":false}],"version":"1.0","authors":["Calium"],"updatedAt":1517439600000,"id":"OMFwhAz0","game":{"id":"oA-XPy3V","name":"Old Coney Island!"}}],"features":["VR","incl. B2S","VPX","LUT","B2S","ROM","POV","Wheel"],"lastCreatedAt":1701903600000,"broken":false,"tutorialFiles":[{"id":"XrxixFUKje","createdAt":1745287317010,"updatedAt":1745287330541,"authors":["Digital Victory"],"title":"\"Old Coney Island\" - Virtual Pinball Tutorial","youtubeId":"btFSFJh_dEQ","game":{"id":"oA-XPy3V","name":"Old Coney Island!"}}]}