{"povFiles":[{"id":"m87i3gYD","game":{"id":"OQh8yjkK","name":"NOBS"},"urls":[{"url":"https:\/\/bit.ly\/POVs_RaJo"}],"version":"1.0","updatedAt":1563141600000,"authors":["RajoJoey"]}],"manufacturer":"Original","broken":false,"lastCreatedAt":1661918400000,"designers":[],"theme":["Cards"],"wheelArtFiles":[{"id":"yqdLFYLJ","game":{"name":"NOBS","id":"OQh8yjkK"},"urls":[{"url":"https:\/\/mega.nz\/#F!p3hREDgB!pEWMJvVQ7t3Sv_TmrxdU-w!52AzHIDR"}],"version":"1.0","updatedAt":1517439600000,"authors":["Calium"]}],"year":2016,"type":"SS","name":"NOBS","id":"OQh8yjkK","b2sFiles":[{"updatedAt":1695644982061,"version":"1.0.0","authors":["Teisen"],"createdAt":1695644947307,"urls":[{"url":"https:\/\/vpuniverse.com\/files\/file\/11418-nobs-borgdog-original-2016\/"}],"id":"r30UrFdhbA","game":{"id":"OQh8yjkK","name":"NOBS"},"imgUrl":"https:\/\/virtualpinballspreadsheet.github.io\/vps-db\/img\/OQh8yjkK_b2s_1695644969318.webp"},{"authors":["fisch"],"updatedAt":1548975600000,"imgUrl":"https:\/\/virtualpinballspreadsheet.github.io\/vps-db\/img\/OQh8yjkK_b2s_1695644880035.webp","features":["2Screens"],"version":"1.0","game":{"id":"OQh8yjkK","name":"NOBS"},"urls":[{"url":"https:\/\/www.vpforums.org\/index.php?app=downloads&showfile=16807"},{"url":"https:\/\/vpuniverse.com\/files\/file\/11423-nobs-orginal-2016-borgdog-12directb2s\/"}],"id":"XZn8oOzj"}],"tableFiles":[{"imgUrl":"https:\/\/virtualpinballspreadsheet.github.io\/vps-db\/img\/OQh8yjkK_table_1662066685756.webp","urls":[{"url":"https:\/\/vpuniverse.com\/files\/file\/11348-nobs-borgdog-2016\/"}],"createdAt":1661918400000,"comment":"Reupload","updatedAt":1746775148085,"id":"Q0FmmEmE","version":"1.2","game":{"id":"OQh8yjkK","name":"NOBS"},"authors":["BorgDog","Arngrim"],"features":["Music","incl. B2S"],"tableFormat":"VPX"}],"updatedAt":1746775148085}