{"tableFiles":[{"features":["Hybrid","VR","no ROM","Mixed Reality"],"authors":["Ext2k","JPSalas","Halen"],"urls":[{"url":"https:\/\/www.vpforums.org\/index.php?app=downloads&showfile=18679"},{"url":"https:\/\/vpuniverse.com\/files\/file\/22102-fan-tas-tic-williams-1972-jpsalas-dt-fs-vr-mr-ext2k-conversion\/"}],"imgUrl":"https:\/\/virtualpinballspreadsheet.github.io\/vps-db\/img\/cWmX7zNm2c_1730213961779.webp","updatedAt":1752544024570,"id":"cWmX7zNm2c","game":{"name":"Fan-Tas-Tic","id":"R5b9h7ZsjZ"},"comment":"B2s required for VR","tableFormat":"VPX","version":"2.0","createdAt":1752537600000},{"id":"U-OQxYQ8z_","createdAt":1728086400000,"urls":[{"url":"https:\/\/www.vpforums.org\/index.php?app=downloads&showfile=18630"}],"authors":["JPSalas","Halen","Pedator"],"tableFormat":"VPX","version":"5.5.0","imgUrl":"https:\/\/virtualpinballspreadsheet.github.io\/vps-db\/img\/U-OQxYQ8z__1727908105438.webp","updatedAt":1739129240525,"features":["no ROM"],"game":{"name":"Fan-Tas-Tic","id":"R5b9h7ZsjZ"}}],"broken":false,"year":1972,"wheelArtFiles":[{"urls":[{"url":"https:\/\/www.vpforums.org\/index.php?app=downloads&showfile=19246"}],"comment":"Logo","version":"1.0","createdAt":1755877635139,"game":{"name":"Fan-Tas-Tic","id":"R5b9h7ZsjZ"},"authors":["deadmanworking"],"updatedAt":1755877657838,"id":"LClSZjgptm"}],"imgUrl":"https:\/\/virtualpinballspreadsheet.github.io\/vps-db\/img\/2V1whhvf7T_1731492534523.webp","designers":["Norm Clark"],"theme":["Dancing","Happiness","Music"],"ipdbUrl":"https:\/\/www.ipdb.org\/machine.cgi?id=820","players":4,"updatedAt":1752544024570,"tutorialFiles":[{"createdAt":1755904241487,"url":"https:\/\/pinballprimer.github.io\/fantastic_G48VE.html","game":{"name":"Fan-Tas-Tic","id":"R5b9h7ZsjZ"},"title":" Fan-Tas-Tic","authors":["Pinball Primer"],"id":"c5bj7u5T9A","updatedAt":1755904241487}],"manufacturer":"Williams","name":"Fan-Tas-Tic","id":"R5b9h7ZsjZ","lastCreatedAt":1752537600000,"b2sFiles":[{"features":["FullDMD"],"game":{"id":"R5b9h7ZsjZ","name":"Fan-Tas-Tic"},"urls":[{"url":"https:\/\/vpuniverse.com\/files\/file\/21842-fan-tas-tic-williams-1972-b2s\/"}],"createdAt":1728000000000,"imgUrl":"https:\/\/virtualpinballspreadsheet.github.io\/vps-db\/img\/Tv7HsZd7nd_1728122456093.webp","authors":["HauntFreaks","Halen"],"id":"Tv7HsZd7nd","updatedAt":1728122488369,"version":"1.0.0"}],"type":"EM","topperFiles":[{"game":{"name":"Fan-Tas-Tic","id":"R5b9h7ZsjZ"},"urls":[{"url":"https:\/\/vpuniverse.com\/files\/file\/21835-fan-tas-tic-williams-1972-topper-video\/"}],"version":"1.0","updatedAt":1729699318111,"authors":["Guet35"],"id":"vztFMJK9uY","createdAt":1728086400000}]}