{"tableFiles":[{"imgUrl":"https:\/\/virtualpinballspreadsheet.github.io\/vps-db\/img\/undefined_table_1691262333225.webp","urls":[{"url":"https:\/\/vpuniverse.com\/files\/file\/14126-bang-genco-1939-v-12-desktop\/"},{"url":"https:\/\/www.vpforums.org\/index.php?app=downloads&showfile=17331"}],"id":"MuKZV7E5Ag","version":"1.2","createdAt":1681689600000,"comment":"Desktop version","game":{"name":"Bang","id":"uRJvD7VhCt"},"tableFormat":"FP","updatedAt":1691262299529,"authors":["Francisco Pozo","Danazo"]},{"urls":[{"url":"https:\/\/vpuniverse.com\/files\/file\/14125-bang-genco-1939-v12\/"},{"url":"https:\/\/www.vpforums.org\/index.php?app=downloads&showfile=17329"}],"version":"Cabinet version","createdAt":1681689600000,"game":{"name":"Bang","id":"uRJvD7VhCt"},"id":"TSbokcKzcc","updatedAt":1691262434295,"imgUrl":"https:\/\/virtualpinballspreadsheet.github.io\/vps-db\/img\/undefined_table_1691262367856.webp","tableFormat":"FP","authors":["Francisco Pozo","Danazo"]}],"ipdbUrl":"https:\/\/www.ipdb.org\/machine.cgi?id=166","year":1939,"lastCreatedAt":1681689600000,"designers":["Leslie M. Hansen"],"theme":["Flipperless"],"players":1,"id":"uRJvD7VhCt","broken":false,"name":"Bang","updatedAt":1681689600000,"manufacturer":"Genco","type":"EM"}