{"topperFiles":[{"updatedAt":1730557679631,"version":"1.0","createdAt":1730557644464,"authors":["GauGau"],"urls":[{"url":"https://vpuniverse.com/files/file/22058-harley-quinn-topper/"}],"game":{"id":"uZVNFOc3","name":"Harley Quinn"},"id":"30C5KBF1EX"},{"id":"ph5no7e_","createdAt":1547337600000,"authors":["Bambi Plattfuss"],"updatedAt":1709555132323,"version":"1.6.6","game":{"id":"uZVNFOc3","name":"Harley Quinn"},"urls":[{"url":"https://vpuniverse.com/files/file/4749-topper-videos/"}]}],"designers":["HauntFreaks"],"tableFiles":[{"createdAt":1720698591547,"imgUrl":"https://virtualpinballspreadsheet.github.io/vps-db/img/gSSpMX8x71_1720698633745.webp","features":["MOD","incl. B2S","Music","incl. Art"],"id":"gSSpMX8x71","urls":[{"url":"https://vpuniverse.com/files/file/20854-harley-quinn-black-and-white-mod-music/"}],"game":{"id":"uZVNFOc3","name":"Harley Quinn"},"comment":"Black and White MOD Music","updatedAt":1760475769204,"authors":["Larouillas","HauntFreaks","BorgDog","Ninuzzu","JPSalas"],"version":"1.0.0","tableFormat":"VPX","edition":"B&W"},{"createdAt":1704150000000,"imgUrl":"https://virtualpinballspreadsheet.github.io/vps-db/img/uZVNFOc3_table_1704019315059.webp","features":["MOD","Music","VPU Patch"],"id":"gBw1FRKVrY","urls":[{"url":"https://vpuniverse.com/files/file/17836-harley-quinn-mod-music/"}],"game":{"id":"uZVNFOc3","name":"Harley Quinn"},"comment":"Music MOD - Use VPURemix System to patch.","updatedAt":1747349817775,"authors":["Larouillas","HauntFreaks","BorgDog","Ninuzzu","JPSalas"],"version":"1.0.0","tableFormat":"VPX"},{"createdAt":1619647200000,"authors":["HauntFreaks","BorgDog","Ninuzzu","JPSalas"],"game":{"id":"uZVNFOc3","name":"Harley Quinn"},"tableFormat":"VPX","id":"iXVpMw9p","comment":"Reskin of Diamond Lady","urls":[{"url":"https://www.vpforums.org/index.php?app=downloads&showfile=13318"},{"url":"https://vpuniverse.com/files/file/6285-harley-quinn-hauntfreaks-2017-in-ultra-mega-real-4k/"}],"features":["4k","incl. Art","incl. B2S","MOD"],"imgUrl":"https://virtualpinballspreadsheet.github.io/vps-db/img/uZVNFOc3_table_1648767476290.webp","version":"1.0.0","updatedAt":1747349859378}],"povFiles":[{"id":"kRPucj8Z","urls":[{"url":"https://bit.ly/POVs_RaJo"}],"version":"1.0","game":{"id":"uZVNFOc3","name":"Harley Quinn"},"authors":["RajoJoey"],"updatedAt":1563141600000}],"broken":false,"b2sFiles":[{"version":"1.1","comment":"","game":{"id":"uZVNFOc3","name":"Harley Quinn"},"updatedAt":1737628848758,"features":["FullDMD"],"id":"s3psfNYW","urls":[{"url":"https://vpuniverse.com/files/file/11830-harley-quinn-hauntfreaks-2017-b2s-with-full-dmd/"}],"imgUrl":"https://virtualpinballspreadsheet.github.io/vps-db/img/s3psfNYW_1737628847505.webp","authors":["HauntFreaks"],"createdAt":1737590400000},{"authors":["Larouillas"],"createdAt":1704019412718,"features":["FullDMD"],"urls":[{"url":"https://vpuniverse.com/files/file/17834-harley-quinn-mod-music/"}],"imgUrl":"https://virtualpinballspreadsheet.github.io/vps-db/img/uZVNFOc3_b2s_1704019446747.webp","id":"EjUuUtrjTW","updatedAt":1704019430097,"version":"1.0.0","game":{"id":"uZVNFOc3","name":"Harley Quinn"}}],"year":2017,"id":"uZVNFOc3","updatedAt":1760475769204,"type":"SS","imgUrl":"https://virtualpinballspreadsheet.github.io/vps-db/img/uZVNFOc3_cover_1649681010783.webp","manufacturer":"Original","theme":["Comics","Superheroes"],"romFiles":[{"id":"9B0uF9qt","urls":[{"url":"https://www.vpforums.org/index.php?app=downloads&showfile=1055"}],"version":"diamond","game":{"id":"uZVNFOc3","name":"Harley Quinn"},"authors":["Destruk"],"updatedAt":1359154800000}],"wheelArtFiles":[{"id":"jROL9MfnTr","updatedAt":1709554937917,"urls":[{"url":"https://vpuniverse.com/files/file/7114-harley-quinn-animated-wheel/"}],"version":"1.0.0","authors":["Mitshiba"],"createdAt":1626912000000,"game":{"id":"uZVNFOc3","name":"Harley Quinn"}},{"version":"1.0.0","id":"8Rj-uI0b","urls":[{"url":"https://vpuniverse.com/files/file/6742-harley-quinn-hauntfreaks-2017-animated/"}],"comment":"Animated","updatedAt":1709490562528,"game":{"id":"uZVNFOc3","name":"Harley Quinn"},"createdAt":1624320000000,"authors":["HauntFreaks"]},{"id":"48UUcA9c","urls":[{"url":"https://mega.nz/#F!p3hREDgB!pEWMJvVQ7t3Sv_TmrxdU-w!52AzHIDR"}],"version":"1.0","game":{"id":"uZVNFOc3","name":"Harley Quinn"},"authors":["Calium"],"updatedAt":1517439600000}],"name":"Harley Quinn","lastCreatedAt":1720698591547}