{"povFiles":[{"updatedAt":1564783200000,"urls":[{"url":"https:\/\/bit.ly\/POVs_RaJo"}],"game":{"id":"VAx9weFV","name":"The Leprechaun King"},"version":"1.0","id":"RWaOrohb","authors":["RajoJoey"]}],"manufacturer":"Original","broken":false,"lastCreatedAt":1617746400000,"designers":["ScottyWic"],"theme":["Fantasy"],"players":4,"type":"SS","year":2019,"name":"The Leprechaun King","id":"VAx9weFV","tableFiles":[{"updatedAt":1617746400000,"game":{"name":"The Leprechaun King","id":"VAx9weFV"},"authors":["ScottyWic","Victoria Fernandez","Danny Tieger","Sofia Silva","Frank Heming","Orbital Creators Club"],"tableFormat":"VPX","createdAt":1617746400000,"urls":[{"url":"https:\/\/orbitalpin.com\/downloads"}],"version":"0.35","id":"65U2ADbg","features":["FlexDMD","incl. PuP"],"imgUrl":"https:\/\/virtualpinballspreadsheet.github.io\/vps-db\/img\/VAx9weFV_table_1683474849399.webp"}],"b2sFiles":[{"authors":["PsychoKiller"],"createdAt":1695996735256,"game":{"name":"The Leprechaun King","id":"VAx9weFV"},"imgUrl":"https:\/\/virtualpinballspreadsheet.github.io\/vps-db\/img\/VAx9weFV_b2s_1695996808184.webp","version":"1.0.0","urls":[{"url":"https:\/\/vpuniverse.com\/files\/file\/11394-leprechaun-king-animated-backglass\/"}],"updatedAt":1695996815180,"id":"pw66lVvVIu"},{"createdAt":1683474784593,"urls":[{"url":"https:\/\/orbitalpin.com\/downloads"}],"comment":"Included with table","game":{"name":"The Leprechaun King","id":"VAx9weFV"},"id":"EXVPyZqsvV","imgUrl":"https:\/\/virtualpinballspreadsheet.github.io\/vps-db\/img\/VAx9weFV_b2s_1683474800095.webp"}],"updatedAt":1617746400000}