{"povFiles":[{"authors":["RajoJoey"],"version":"1.0","urls":[{"url":"https://bit.ly/POVs_RaJo"}],"game":{"id":"wEOAp90_","name":"Medusa"},"id":"TvqfB6hj","updatedAt":1563141600000}],"manufacturer":"Bally","topperFiles":[{"createdAt":1740500357981,"authors":["Hursty"],"urls":[{"url":"https://vpuniverse.com/files/file/23358-medusa-bally-1981-hursty-toppers/"}],"game":{"id":"wEOAp90_","name":"Medusa"},"id":"97pkjzfY8A","updatedAt":1740500366418}],"mediaPackFiles":[{"authors":["Bitupset"],"version":"1.0.0","urls":[{"url":"https://www.vpforums.org/index.php?app=downloads&showfile=4393"}],"game":{"id":"wEOAp90_","name":"Medusa"},"id":"z22z8JZ6","updatedAt":1290639600000}],"lastCreatedAt":1689912000000,"MPU":"Bally MPU AS-2518-35","broken":false,"imgUrl":"https://virtualpinballspreadsheet.github.io/vps-db/img/wEOAp90__b2s_1669590322438.webp","designers":["Wally Welch"],"theme":["Fantasy","Mythology"],"players":4,"wheelArtFiles":[{"createdAt":1693313108620,"version":"1.0.0","updatedAt":1709510374375,"authors":["Coolman"],"comment":"Animated","game":{"id":"wEOAp90_","name":"Medusa"},"id":"sYTb_ppLQk","urls":[{"url":"https://vpuniverse.com/files/file/12954-medusa-animated-wheel/"}]},{"urls":[{"url":"https://vpuniverse.com/files/file/15238-medusa-bally-1981-wheels/"}],"game":{"id":"wEOAp90_","name":"Medusa"},"updatedAt":1693313096951,"version":"1.0.0","authors":["GauGau"],"createdAt":1693313092610,"id":"0eu0whASVE"},{"updatedAt":1709510386885,"authors":["Hiylow"],"id":"-UqMykRTSM","urls":[{"url":"https://vpuniverse.com/files/file/15172-medusa-pretty-to-ugly-transformation-wheel-bally-1981/"}],"createdAt":1693312975320,"version":"1.0.0","comment":"Animated","game":{"id":"wEOAp90_","name":"Medusa"}},{"authors":["Calium"],"version":"1.0","urls":[{"url":"https://mega.nz/?fbclid=IwAR3VY7WR8hFJVDAM2ARGqF5JXRsGRDKziFuyLdDPIGHvf4Z0TARpnz0EL1E#F!IFsxBbCD!04cfuNEJi5hwuYxL6CvQIg"}],"game":{"id":"wEOAp90_","name":"Medusa"},"id":"f4wVtnFz","updatedAt":1548025200000}],"year":1981,"type":"SS","ipdbUrl":"http://www.ipdb.org/machine.cgi?id=1565","name":"Medusa","id":"wEOAp90_","tableFiles":[{"imgUrl":"https://virtualpinballspreadsheet.github.io/vps-db/img/wEOAp90__table_1689772561549.webp","id":"uX6tpMMHin","features":["Hybrid","VR","Fleep","LUT","nFozzy"],"version":"2.0.1","comment":"With VR Room, Desktop, Cabinet modes","game":{"id":"wEOAp90_","name":"Medusa"},"urls":[{"url":"https://vpuniverse.com/files/file/15137-medusa-bally-1981-w-vr-room/"}],"createdAt":1689912000000,"updatedAt":1689950444243,"authors":["UnclePaulie","EBisLit","Iaakki","JPSalas"],"tableFormat":"VPX"},{"authors":["JPSalas"],"updatedAt":1669590250987,"urls":[{"url":"https://www.vpforums.org/index.php?app=downloads&showfile=12926"}],"version":"4.0.2","tableFormat":"VPX","imgUrl":"https://virtualpinballspreadsheet.github.io/vps-db/img/wEOAp90__table_1669590283906.webp","game":{"id":"wEOAp90_","name":"Medusa"},"createdAt":1669158000000,"id":"_cFckI6F","features":["LUT"]},{"comment":"VR Room","urls":[{"url":"https://vpuniverse.com/files/file/7305-vr-room-medusa-bally-1981-100/","broken":false},{"url":"https://www.vpforums.org/index.php?app=downloads&showfile=16067","broken":false}],"updatedAt":1749638612202,"features":["VR","LUT"],"imgUrl":"https://virtualpinballspreadsheet.github.io/vps-db/img/wEOAp90__table_1672919034786.webp","authors":["RajoJoey","JPSalas"],"createdAt":1628978400000,"game":{"id":"wEOAp90_","name":"Medusa"},"id":"QwDn4KfxSu","version":"1.0.0","tableFormat":"VPX"}],"b2sFiles":[{"id":"ljJXPPCzG8","createdAt":1747526400000,"updatedAt":1749237833002,"urls":[{"url":"https://vpuniverse.com/files/file/25468-medusa-bally-1981-b2s-with-full-dmd/","broken":false}],"authors":["Rtx"],"features":["FullDMD"],"version":"1.0.0","imgUrl":"https://virtualpinballspreadsheet.github.io/vps-db/img/ljJXPPCzG8_1749237831806.webp","game":{"id":"wEOAp90_","name":"Medusa"}},{"createdAt":1690070400000,"urls":[{"url":"https://vpuniverse.com/files/file/15159-medusa-bally-1981-avant-garde-pretty-or-ugly-b2s-with-full-dmd/"}],"updatedAt":1710270195778,"imgUrl":"https://virtualpinballspreadsheet.github.io/vps-db/img/wEOAp90__b2s_1690106516029.webp","features":["FullDMD"],"id":"KupYkEi2ZD","game":{"id":"wEOAp90_","name":"Medusa"},"authors":["Hiylow"],"version":"1.0.0"},{"version":"2.5","id":"zTVGMra15e","authors":["HauntFreaks","BallStuck"],"imgUrl":"https://virtualpinballspreadsheet.github.io/vps-db/img/wEOAp90__b2s_1689820820532.webp","createdAt":1689638400000,"urls":[{"url":"https://vpuniverse.com/files/file/12171-medusa-bally-1981-prototype-authentic-lighting/"}],"updatedAt":1710270229168,"game":{"id":"wEOAp90_","name":"Medusa"},"features":["3Screens"]},{"urls":[{"url":"https://vpuniverse.com/files/file/13961-medusa-bally-1981-fantasy-b2s-2scr/"}],"imgUrl":"https://virtualpinballspreadsheet.github.io/vps-db/img/wEOAp90__b2s_1689706836482.webp","features":["2Screens","3Screens"],"createdAt":1680825600000,"updatedAt":1710270210193,"authors":["Ryguy417"],"game":{"id":"wEOAp90_","name":"Medusa"},"id":"MWcts-Aui7","version":"2.0.1"},{"game":{"id":"wEOAp90_","name":"Medusa"},"createdAt":1675900800000,"features":["FullDMD"],"id":"95bZB2OOx6","version":"3.0","authors":["Ryguy417","HauntFreaks"],"updatedAt":1710270218553,"imgUrl":"https://virtualpinballspreadsheet.github.io/vps-db/img/wEOAp90__b2s_1692619775552.webp","urls":[{"url":"https://vpuniverse.com/files/file/12934-medusa-bally-1981-fantasy-b2s-with-full-dmd/"}]},{"urls":[{"url":"https://vpuniverse.com/files/file/12157-medusa-bally-1981-uncensored-b2s-directb2s-backglass/"}],"version":"1.0.0","game":{"id":"wEOAp90_","name":"Medusa"},"createdAt":1668556800000,"authors":["BallStuck"],"imgUrl":"https://virtualpinballspreadsheet.github.io/vps-db/img/wEOAp90__b2s_1697723824975.webp","features":["2Screens"],"updatedAt":1710270241582,"id":"DbE8GqQWt9"},{"features":["2Screens"],"urls":[{"url":"https://www.vpforums.org/index.php?app=downloads&showfile=12947"}],"id":"lmqL8ZZR","version":"1.0","updatedAt":1710270258788,"authors":["HauntFreaks"],"createdAt":1499040000000,"game":{"id":"wEOAp90_","name":"Medusa"},"imgUrl":"https://virtualpinballspreadsheet.github.io/vps-db/img/wEOAp90__b2s_1669590322438.webp"}],"updatedAt":1749638612202,"romFiles":[{"authors":["Destruk"],"version":"medusa","urls":[{"url":"https://www.vpforums.org/index.php?app=downloads&showfile=659"}],"game":{"id":"wEOAp90_","name":"Medusa"},"id":"YCVL8tpz","updatedAt":1359241200000}]}