{"name":"Phase II","type":"EM","manufacturer":"J. Esteban","year":1975,"theme":["Mysticism"],"tableFiles":[{"id":"bHYR0mLQv3","createdAt":1689631200000,"updatedAt":1689773123724,"urls":[{"url":"https://www.vpforums.org/index.php?app=downloads&showfile=17567"},{"url":"https://vpuniverse.com/files/file/15252-phase-ii-j-esteban-1975_teisen_mod/"}],"version":"1.0","comment":"Teisen MOD","authors":["Teisen","Loserman76","Carlos Guizzo","Halen"],"tableFormat":"VPX","theme":["Mystic"],"imgUrl":"https://virtualpinballspreadsheet.github.io/vps-db/img/x6df4mgv_table_1689773179489.webp","features":["MOD"]},{"createdAt":1628200800000,"theme":["Mystic"],"updatedAt":1638196308564,"urls":[{"url":"https://vpuniverse.com/forums/files/file/7226-phase-ii-j-esteban-1975/"}],"features":["incl. B2S","incl. Art","no ROM"],"authors":["Loserman76"],"imgUrl":"https://virtualpinballspreadsheet.github.io/vps-db/img/undefined_table_1638196286811.webp","version":"1.0a","tableFormat":"VPX","id":"iyIWDkZX"}],"ipdbUrl":"https://www.ipdb.org/machine.cgi?id=5787","imgUrl":"https://virtualpinballspreadsheet.github.io/vps-db/img/e9f874ea-aa91-4f1f-8313-d001b89f9c76_cover_1638196401330.webp","features":["MOD","VPX","incl. B2S","incl. Art","no ROM","B2S"],"broken":false,"updatedAt":1689631200000,"lastCreatedAt":1689631200000,"id":"x6df4mgv","b2sFiles":[{"id":"ZwcjH4MSej","createdAt":1670974594536,"imgUrl":"https://virtualpinballspreadsheet.github.io/vps-db/img/x6df4mgv_b2s_1670974605754.webp","urls":[{"url":"https://vpuniverse.com/forums/files/file/7226-phase-ii-j-esteban-1975/"}],"version":"1.0a","updatedAt":1670974610803,"authors":["Loserman76","Carlos Guizzo","Halen"],"comment":"Included with table"}]}