{"topperFiles":[{"version":"1.0","game":{"id":"x9i_W1Ql","name":"Seawitch"},"id":"7F-2MrApf1","authors":["Guet35"],"createdAt":1730557730159,"updatedAt":1730557746080,"urls":[{"url":"https://vpuniverse.com/files/file/22137-seawitch-stern-1980-topper-video/"}]},{"urls":[{"url":"https://vpuniverse.com/files/file/21293-seawitch-stern-1980-topper-video/"}],"game":{"id":"x9i_W1Ql","name":"Seawitch"},"updatedAt":1723384216147,"createdAt":1723384190180,"authors":["Purcho"],"version":"1.0","id":"eP3R3tu2xT"}],"manufacturer":"Stern","designers":["Mike Kubin"],"updatedAt":1749640627487,"id":"x9i_W1Ql","players":4,"tableFiles":[{"tableFormat":"VPX","imgUrl":"https://virtualpinballspreadsheet.github.io/vps-db/img/1MTsorv_ku_1738073988258.webp","urls":[{"url":"https://www.vpforums.org/index.php?app=downloads&showfile=14916"}],"comment":"","id":"1MTsorv_ku","game":{"id":"x9i_W1Ql","name":"Seawitch"},"updatedAt":1738073989646,"authors":["JPSalas","Martin Brunker"],"version":"5.5.0","features":["LUT"],"createdAt":1734134400000},{"features":["Fleep","nFozzy"],"authors":["Bord"],"version":"1.1","imgUrl":"https://virtualpinballspreadsheet.github.io/vps-db/img/36d4a615f0e946404aaf662b246172cc_table_1638616864060.webp","game":{"id":"x9i_W1Ql","name":"Seawitch"},"updatedAt":1638616833056,"id":"9f7hh91z","urls":[{"url":"https://vpuniverse.com/files/file/6534-seawitch-stern-1980-bord/"}],"createdAt":1622498400000,"tableFormat":"VPX"},{"authors":["RajoJoey","JPSalas"],"features":["VR","MOD","LUT"],"comment":"VR Room","urls":[{"url":"https://vpuniverse.com/files/file/6551-vr-room-seawitch-stern-1980-100/","broken":false},{"url":"https://www.vpforums.org/index.php?app=downloads&showfile=15761","broken":false}],"updatedAt":1749640627487,"tableFormat":"VPX","createdAt":1622412000000,"imgUrl":"https://virtualpinballspreadsheet.github.io/vps-db/img/x9i_W1Ql_table_1672920339357.webp","id":"0jQHGOu6Ch","game":{"id":"x9i_W1Ql","name":"Seawitch"},"version":"1.0.1"},{"id":"M2cO9PbC","version":"3.0-1.0","updatedAt":1687310966842,"features":["FSS","MOD"],"imgUrl":"https://virtualpinballspreadsheet.github.io/vps-db/img/x9i_W1Ql_table_1687310969760.webp","authors":["Morttis","Arconovum","JPSalas"],"createdAt":1605654000000,"tableFormat":"VPX","comment":"FSS (Full Single Screen) MOD","game":{"id":"x9i_W1Ql","name":"Seawitch"},"urls":[]},{"authors":["flash62"],"tableFormat":"VPX","urls":[{"url":"https://www.vpforums.org/index.php?app=downloads&showfile=13558"}],"createdAt":1528149600000,"game":{"id":"x9i_W1Ql","name":"Seawitch"},"id":"RcuBK-kl","updatedAt":1747642999016,"version":"1.0","imgUrl":"https://virtualpinballspreadsheet.github.io/vps-db/img/x9i_W1Ql_table_1648984486488.webp","features":[]},{"features":["incl. B2S"],"updatedAt":1528063200000,"game":{"id":"x9i_W1Ql","name":"Seawitch"},"authors":["HauntFreaks","32assassin"],"version":"2.0","imgUrl":"https://virtualpinballspreadsheet.github.io/vps-db/img/x9i_W1Ql_table_1693217806926.webp","tableFormat":"VPX","comment":"Reupload","urls":[{"url":"https://vpuniverse.com/files/file/6342-seawitch-stern-1980/"}],"id":"THm3ohiJ","createdAt":1528063200000}],"type":"SS","theme":["Fantasy"],"wheelArtFiles":[{"authors":["Calium"],"id":"_datCRQJ","urls":[{"url":"https://mega.nz/#F!p3hREDgB!pEWMJvVQ7t3Sv_TmrxdU-w!52AzHIDR"}],"updatedAt":1517439600000,"version":"1.0","game":{"id":"x9i_W1Ql","name":"Seawitch"}}],"name":"Seawitch","lastCreatedAt":1734134400000,"mediaPackFiles":[{"updatedAt":1290639600000,"version":"1.0.0","id":"KQjTxpig","game":{"id":"x9i_W1Ql","name":"Seawitch"},"urls":[{"url":"https://www.vpforums.org/index.php?app=downloads&showfile=4410"}],"authors":["Bitupset"]}],"broken":false,"MPU":"Stern M-200 MPU","b2sFiles":[{"id":"88agPMZvAy","updatedAt":1745811387129,"createdAt":1745811330512,"urls":[{"url":"https://vpuniverse.com/files/file/24958-seawitch-stern-1980-alt-b2s/"}],"authors":["HauntFreaks"],"game":{"id":"x9i_W1Ql","name":"Seawitch"},"features":["2Screens"],"version":"1.0.0","comment":"Alternate, remastered 3k image","imgUrl":"https://virtualpinballspreadsheet.github.io/vps-db/img/88agPMZvAy_1745811377056.webp"},{"updatedAt":1745811350964,"createdAt":1745107200000,"imgUrl":"https://virtualpinballspreadsheet.github.io/vps-db/img/0iAv2lXBu-_1745811268701.webp","game":{"id":"x9i_W1Ql","name":"Seawitch"},"urls":[{"url":"https://vpuniverse.com/files/file/24959-seawitch-stern-1980-b2s/"}],"comment":"remastered 3k image","authors":["HauntFreaks"],"features":["2Screens","3Screens"],"version":"1.0.0","id":"0iAv2lXBu-"},{"updatedAt":1710185366245,"features":["FullDMD"],"version":"1.0.0","id":"1YVLU78-5i","imgUrl":"https://virtualpinballspreadsheet.github.io/vps-db/img/1YVLU78-5i_1710185354967.webp","authors":["HauntFreaks"],"game":{"id":"x9i_W1Ql","name":"Seawitch"},"urls":[{"url":"https://vpuniverse.com/files/file/12534-seawitch-stern-1980-b2s-with-full-dmd/"}],"createdAt":1671926400000},{"urls":[{"url":"https://vpuniverse.com/files/file/2200-seawitchstern1980/"}],"createdAt":1511049600000,"game":{"id":"x9i_W1Ql","name":"Seawitch"},"version":"2.0","imgUrl":"https://virtualpinballspreadsheet.github.io/vps-db/img/x9i_W1Ql_b2s_1648984559942.webp","id":"zAX-gyWa","authors":["Wildman"],"updatedAt":1710185336932}],"year":1980,"romFiles":[{"id":"g1KPpXTaVE","createdAt":1729555200000,"updatedAt":1749292440969,"urls":[{"url":"https://vpuniverse.com/files/file/22023-seawitch-mod-rev-93/","broken":false}],"authors":["CarnyPriest"],"comment":"Mod rev. 9.3","version":"seawitchf","game":{"id":"x9i_W1Ql","name":"Seawitch"}},{"id":"es3CecKtUa","createdAt":1729555200000,"updatedAt":1749292487570,"urls":[{"url":"https://vpuniverse.com/files/file/22022-seawitch-mod-rev-9/","broken":false}],"authors":["CarnyPriest"],"comment":"MOD rev. 9","version":"seawitche","game":{"id":"x9i_W1Ql","name":"Seawitch"}},{"urls":[{"url":"https://www.vpforums.org/index.php?app=downloads&showfile=742"}],"game":{"id":"x9i_W1Ql","name":"Seawitch"},"updatedAt":1359327600000,"authors":["Destruk"],"id":"DRckOWbr","createdAt":1359331200000,"version":"seawitch"}],"imgUrl":"https://virtualpinballspreadsheet.github.io/vps-db/img/x9i_W1Ql_b2s_1693348649036.webp","ipdbUrl":"http://www.ipdb.org/machine.cgi?id=2089","povFiles":[{"authors":["RajoJoey"],"id":"l0t8-ZaZ","urls":[{"url":"https://bit.ly/POVs_RaJo"}],"updatedAt":1563141600000,"version":"1.0","game":{"id":"x9i_W1Ql","name":"Seawitch"}}]}