{"id":"xvdDmljXmX","updatedAt":1715985094294,"manufacturer":"Original","name":"Men in Black Trilogy","year":2024,"theme":["Science Fiction","Movie"],"designers":[],"type":"SS","players":4,"tableFiles":[{"id":"hA7QRdZvv6","createdAt":1715904000000,"updatedAt":1715985094294,"urls":[{"url":"https://vpuniverse.com/files/file/20036-men-in-black-trilogy/","broken":false}],"authors":["Marty02","JPSalas","James","Outhere"],"features":["no ROM","incl. B2S","incl. PuP","incl. Art","SSF"],"tableFormat":"VPX","version":"3.2","imgUrl":"https://virtualpinballspreadsheet.github.io/vps-db/img/hA7QRdZvv6_1715717922971.webp","game":{"id":"xvdDmljXmX","name":"Men in Black Trilogy"}}],"b2sFiles":[{"id":"BxzesHtxv3","createdAt":1715718038664,"updatedAt":1715718071813,"urls":[{"url":"https://vpuniverse.com/files/file/20036-men-in-black-trilogy/","broken":false}],"authors":["Marty02"],"features":[],"version":"3.0","comment":"Included with table download","imgUrl":"https://virtualpinballspreadsheet.github.io/vps-db/img/BxzesHtxv3_1715718070600.webp","game":{"id":"xvdDmljXmX","name":"Men in Black Trilogy"}}],"lastCreatedAt":1715904000000}